simpleworkspace/__lazyimporter__.py
simpleworkspace/app.py
simpleworkspace/loader.py
simpleworkspace/logproviders.py
simpleworkspace/settingsproviders.py
simpleworkspace/assets/__init__.py
simpleworkspace/assets/audio/alarms/Siren.wav
simpleworkspace/assets/audio/notifications/Completed.wav
simpleworkspace/assets/audio/notifications/Error.wav
simpleworkspace/assets/icons/ErrorCircle.png
simpleworkspace/assets/icons/InfoCircle.png
simpleworkspace/assets/icons/QuestionCircle.png
simpleworkspace/assets/icons/WarningCircle.png
simpleworkspace/db/dbfactory.py
simpleworkspace/db/fluentsqlbuilder.py
simpleworkspace/db/loader.py
simpleworkspace/gui/dialogs.py
simpleworkspace/gui/loader.py
simpleworkspace/io/directory.py
simpleworkspace/io/file.py
simpleworkspace/io/loader.py
simpleworkspace/io/path.py
simpleworkspace/io/audio/loader.py
simpleworkspace/io/audio/play.py
simpleworkspace/io/parsers/archive.py
simpleworkspace/io/parsers/csv.py
simpleworkspace/io/parsers/loader.py
simpleworkspace/io/parsers/logging.py
simpleworkspace/io/parsers/m3u8.py
simpleworkspace/io/parsers/json5/__init__.py
simpleworkspace/io/parsers/json5/__main__.py
simpleworkspace/io/parsers/json5/arg_parser.py
simpleworkspace/io/parsers/json5/host.py
simpleworkspace/io/parsers/json5/lib.py
simpleworkspace/io/parsers/json5/parser.py
simpleworkspace/io/parsers/json5/tool.py
simpleworkspace/io/parsers/json5/version.py
simpleworkspace/io/parsers/toml/__init__.py
simpleworkspace/io/parsers/toml/decoder.py
simpleworkspace/io/parsers/toml/encoder.py
simpleworkspace/io/parsers/toml/ordered.py
simpleworkspace/io/parsers/toml/tz.py
simpleworkspace/packages/debug/profiler.py
simpleworkspace/packages/deprecated/utility/encryption/_legacy_crosscryptv1.py
simpleworkspace/packages/network/proxy/nordvpn.py
simpleworkspace/packages/network/servers/basicserver/__init__.py
simpleworkspace/packages/network/servers/basicserver/server.py
simpleworkspace/packages/network/servers/basicserver/model/commobjects.py
simpleworkspace-1.2.410.dist-info/licenses/LICENSE.md
simpleworkspace-1.2.410.dist-info/METADATA
simpleworkspace-1.2.410.dist-info/WHEEL
simpleworkspace-1.2.410.dist-info/top_level.txt
simpleworkspace-1.2.410.dist-info/RECORD
