Metadata-Version: 2.4
Name: simpleworkspace
Version: 1.2.410
Summary: Rapid protyping library
License: Copyright (C) 2022 simpleworkspace - All Rights Reserved
Requires-Python: >=3.11
License-File: LICENSE.md
Requires-Dist: requests
Requires-Dist: cryptography
Dynamic: license-file
